Metadata-Version: 2.1
Name: mgarch-setup-fix
Version: 0.2.0
Summary: DCC-GARCH(1,1)
Home-page: https://github.com/srivastavaprashant/mgarch
Author: Prashant Srivastava
Author-email: srivastava.prashant898@gmail.com
License: MIT
Download-URL: https://github.com/srivastavaprashant/mgarch/archive/0.2.0.tar.gz
Keywords: volatility,multivariate,garch
Platform: UNKNOWN
Classifier: Development Status :: 3 - Alpha
Classifier: Intended Audience :: Developers
Classifier: Topic :: Software Development :: Build Tools
Classifier: License :: OSI Approved :: MIT License
Classifier: Programming Language :: Python :: 3
Classifier: Programming Language :: Python :: 3.4
Classifier: Programming Language :: Python :: 3.5
Classifier: Programming Language :: Python :: 3.6
